compressTraj/Classes.py
compressTraj/Helpers.py
compressTraj/__init__.py
compressTraj-0.1.dist-info/METADATA
compressTraj-0.1.dist-info/WHEEL
compressTraj-0.1.dist-info/top_level.txt
compressTraj-0.1.dist-info/RECORD
