Metadata-Version: 2.1
Name: compressTraj
Version: 0.1
Summary: Using AutoEncoders to compress molecular dynamics trajectories.
Home-page: https://github.com/yourusername/my_project
Author: SerpentByte
Author-email: wasim.abdul.1995@gmail.com
Classifier: Programming Language :: Python :: 3
Classifier: License :: OSI Approved :: MIT License
Classifier: Operating System :: OS Independent
Requires-Python: >=3.6
Requires-Dist: numpy
Requires-Dist: torch
Requires-Dist: pytorch-lightning
Requires-Dist: MDAnalysis
Requires-Dist: tqdm
